Workbook
Name BOQ_FLAG: Cover!$A$1
Name CFG_HEADER_LINE: Disclaimer!$C$5
Name CFG_HEADER_LINE: 'Solution Introduction'!$C$5
Name CFGTEMPLATEROW: Disclaimer!$C$15
Name CFGTEMPLATEROW: 'Solution Introduction'!#REF!
Name CFGTITLE: Discount!$C$10:$G$10
Name CREATE_DATE: Cover!$C$21
Name DISCLAIMER_TOTALROW: Disclaimer!$A$3
Name DISCLAIMER_TOTALROW: 'Solution Introduction'!$A$3
Name DYNAMIC_DISCLAIMER: Disclaimer!$C$14
Name DYNAMIC_DISCLAIMER: 'Solution Introduction'!#REF!
Name PRODUCT_DISCLAIMER: Disclaimer!$C$15
Name PRODUCT_DISCLAIMER: 'Solution Introduction'!#REF!
Name ProductCode: "null"
Name ProductCode: "null"
Name ProductCode: "null"
Name PROJECTCODE: Cover!$J$2
Name projinfo: Discount!$C$10:$G$28
Name QF_SYS_BRANCHOFFICE: Discount!$E$14
Name QF_SYS_CALC_DECIMAL: Discount!$E$28
Name QF_SYS_CONTRACT_NUMBER: Discount!$E$17
Name QF_SYS_DECIMAL_FORMAT: Discount!$E$26
Name QF_SYS_DISPLAY_DECIMAL: Discount!$E$27
Name QF_SYS_LISTPRICECURRENCY_CURRENCY: Discount!$E$24
Name QF_SYS_LISTPRICECURRENCY_CUSTOM: Discount!$E$23
Name QF_SYS_OPERATOR: Discount!$E$11
Name QF_SYS_PRODUCT_LINE: Discount!$E$25
Name QF_SYS_PROJNAME: Discount!$E$12
Name QF_SYS_QUOTATION_NAME: Discount!$E$19
Name QF_SYS_QUOTATION_NO: Discount!$E$16
Name QF_SYS_QUOTATION_PONUMBER: Discount!$E$18
Name QF_SYS_RFP_NO: Discount!$E$15
Name QF_SYS_SECURITY_FLAG: Discount!$E$22
Name QF_SYS_SERVICE_ONLY: Discount!$E$21
Name QF_SYS_SIGNER: [1]Discount!$E$13
Name QF_SYS_SIGNER: Discount!$E$13
Name QF_SYS_VALIDITY_DATE: Discount!$E$20
Name QUOTATIONBY: Cover!$B$7
Name QUOTATIONNO: Cover!$J$3
Name SheetByID: "None"
Name SheetByID: "None"
Name SheetByID: "None"
Name SheetByID: "None"
Name SheetByName: "None"
Name SheetByName: "None"
Name SheetByName: "None"
Name SheetByName: "None"
Name SheetName: "Cover"
Name SheetName: "Disclaimer"
Name SheetName: "Discount"
Name SheetName: "Disclaimer"
Name SheetType: "100001"
Name SheetType: "100002"
Name SheetType: "1000014"
Name SheetType: "100002"
Name SOLUTIONNAME: Cover!$B$6
Name VALID_AREA: Cover!$A$1:$F$22
Name VALID_AREA: Disclaimer!$A$1:$C$20
Name VALID_AREA: 'Solution Introduction'!$A$1:$C$6
Name VALIDDATE: Disclaimer!$A$2

Sheet Discount
C1: COL_KEY.0 | E1: COL_VALUE.0
C9: ProjInfo
C10: Parameter Name | E10: Value
A11: Operator.0,null | C11: Operator | E11: China Mobile Hong Kong Company Limited
A12: Project Name.0,null | C12: Project Name | E12: TLF ESB EOS relacement-V3.0 1004
A13: Signer.0,null | C13: Signer
A14: Branch Office.0,null | C14: Branch Office | E14: Hong Kong Rep Office
A15: RFP NO./Name.0,null | C15: RFP NO./Name
A16: Quotation Number.0,null | C16: Quotation Number | E16: 000000522472202110040001
A17: Contract Number.0,null | C17: Contract Number | E17: P0002109290022
A18: PO Number.0,null | C18: PO Number
A19: Solution Name.0,null | C19: Solution Name | E19: Solution
A20: Validity Date.0,null | C20: Validity Date | E20: 2022-01-05
A21: SERVICE ONLY.0,null | C21: SERVICE ONLY | E21: 0
A22: Security Description.0,null | C22: Security Description
A23: IsCustom.0,null | C23: IsCustom | E23: 0
A24: Currency.0,null | C24: Currency | E24: USD
A25: Product Line Flag.0,null | C25: Product Line Flag
A26: Decimal Digits Format.0,null | C26: Decimal Digits Format
A27: Displaying Decimal Places.0,null | C27: Displaying Decimal Places | E27: 2
A28: Calculating Decimal Places.0,null | C28: Calculating Decimal Places | E28: 2

Sheet Cover
A1: 1
B5: PRICE SCHEDULE
B6: Har-Per - Clinica Union Medica - Datawarehouse Project
B7: PHASE:
B8: Quotation Provided by: Miguel Matos
C20: www.huaweicloud.com
C21: =TEXT(TODAY(),"yyyy - mm - dd") -> 2026 - 08 - 05

Sheet Disclaimer
C7: QUOTATION DISCLAIMER
C9: 1. By receiving this offer the Partner/Customer expressly accepts and agrees on the following:
C10: ­ This offer itself and/or the terms included in it, including but not limited to prices and/or costs quoted in this offer, are valid from the quotation date till 6 months.
C11: ­ This offer constitutes mere information and an invitation to the Partner/Customer, not binding for Huawei, to submit to Huawei its petition of Purchase Order.
C12: ­ The terms contained in this offer and/or this offer itself shall be valid and enforceable by the Partner/customer and binding for Huawei only in case of Huawei and the Partner/Customer formalizes, according to Huawei contracting processes,a Purchase Order that includes Huawei terms and conditions.
C13: ­ The above mentioned Huawei terms and conditions shall be the only terms and conditions applicable to the provision of services described in this offer and therefore they shall govern the provision of the mentioned services.
C14: ­ Huawei may, at its sole discretion and without any compensation (including but not limited to indemnification for damages) in favor of the Partner/Customer, accepts or rejects the formalization of a Purchase Order.
C15: ­ Any Partner/Customer terms and/or conditions, communicated (orally, in writing or trough any other mean) or not, shall be void and not applicable for the provision of the services described in the present offer.
C16: 2. The preceding price is for reference only and may vary from the final price in your bill. Pay as you use.
C17: 3. The price in this offer only covers the specific items in the BOQ list, excluding the optional parts.
C18: 4. In case that any subsequent legislative regulations including but not limited to tax law in the territory of the Partner/Customer affects the pricing, the pricing should be adjusted accordingly.
C19: 5. Huawei shall be entitled to select another supplier if the nominated supplier is no longer qualified or in default of its performance.
C20: 6. Nevertheless, Huawei shall be allowed to provide alternative supply solution in case of discontinuation of original product.
C21: 44519
C24: =QF_SYS_SIGNER

Sheet Solution Introduction
C21: 44519

Sheet Price Calculator Summary
A5: Global Summary
B7: ITEM | C7: Monthly Price After Discount
B8: Compute - PROD | C8: ='Compute - PROD'!B17 -> 1094.26
B9: Compute - DEV | C9: ='Compute - DEV'!B19 -> 989.92
B10: Storage | C10: =Storage!B17 -> 343.62
B11: Connectivity | C11: =Connectivity!B16 -> 454.19
B12: Security | C12: =Security!B14 -> 55.2
B13: Support | C13: =Support!B14 -> 300
B15: Monthly Total | C15: =SUM(C8:C13) -> 3237.19
A16: The preceding price is for reference only and may vary from the final price in your bill

Sheet Compute - PROD
A5: CALCULADORA DE SERVICIOS
A7: ="Price Calculator "&TEXT(TODAY(),"mmm dd, yyyy") -> Price Calculator Aug 05, 2026
A8: Required | B8: Service | C8: Description | D8: Region | E8: AZ | F8: Billing Mode | G8: Purchase Amount | H8: Unit | I8: Quantity | J8: Specifications | K8: Unit Price (USD) | L8: Monthly Price (USD)
A9: Datawarehouse Service (DWS) Cluster | B9: Data Warehouse Service 1 | C9: Data Warehouse Service | D9: LA-Mexico City2 | E9: General AZ | F9: Monthly | G9: 1 | H9: month | I9: 1 | J9: 250 GB * 3 Node; 4U16G.4DPU|Decoupled Storage And Compute|X86|4 vCPUs | 16 GB * 3 Node; 2* 100 GB; | K9: 840.9 | L9: 840.9
A10: Server #1 - Servidor ETL | 8vCPU 64GB RAM | Disk1: 1 TB | B10: Elastic Cloud Server 1 | C10: Servidor ETL | D10: LA-Mexico City2 | E10: General AZ | F10: RI | G10: 1 | I10: 1 | J10: Ubuntu | Ubuntu 24.04 server 64bit; x86 | General computing | x0.2u.16g | 2 vCPUs | 16GiB | No Upfront | 1 Year; General Purpose SSD | 500GB; | K10: =933.84/12 -> 77.82 | L10: 77.82
A11: Server #2 - Gateway BI | 4vCPU 32GB RAM | Disk1: 500 GB | B11: Elastic Cloud Server 2 | C11: Gateway BI | D11: LA-Mexico City2 | E11: General AZ | F11: RI | G11: 1 | I11: 1 | J11: Ubuntu | Ubuntu 24.04 server 64bit; x86 | General computing | x0.2u.8g | 2 vCPUs | 8GiB | No Upfront | 1 Year; General Purpose SSD | 500GB; | K11: =865.44/12 -> 72.12 | L11: 72.12
A12: Datawarehouse Load Balancer | B12: Elastic Load Balance 1 | C12: Elastic Load Balance | D12: LA-Mexico City2 | E12: General AZ | F12: Pay-per-use | G12: 744 | H12: hours | I12: 1 | J12: General AZ | 20 LCU; | K12: 103.42 | L12: 103.42
A13: Total Price | K13: =SUM(INDIRECT(ADDRESS(1,COLUMN())&":"&ADDRESS(ROW()-1,COLUMN()))) -> 1094.26 | L13: =SUM(INDIRECT(ADDRESS(1,COLUMN())&":"&ADDRESS(ROW()-1,COLUMN()))) -> 1094.26
A14: The preceding price is for reference only and may vary from the final price in your bill
A17: Monthly Price | B17: =L13 -> 1094.26

Sheet Compute - DEV
A5: CALCULADORA DE SERVICIOS
A7: ="Price Calculator "&TEXT(TODAY(),"mmm dd, yyyy") -> Price Calculator Aug 05, 2026
A8: Required | B8: Service | C8: Description | D8: Region | E8: AZ | F8: Billing Mode | G8: Purchase Amount | H8: Unit | I8: Quantity | J8: Specifications | K8: Unit Price (USD) | L8: Monthly Price (USD)
A9: Datawarehouse Service (DWS) Cluster | B9: Data Warehouse Service 2 | C9: Data Warehouse Service - Dev | D9: LA-Mexico City2 | E9: General AZ | F9: Monthly | G9: 1 | H9: month | I9: 1 | J9: 200 GB * 3 Node; 4U16G.4DPU|Decoupled Storage And Compute|X86|4 vCPUs | 16 GB * 3 Node; 2* 100 GB; | K9: 797.4 | L9: 797.4
A10: Server #1 - Servidor ETL | 4vCPU 32GB RAM | Disk1: 500 GB | B10: Elastic Cloud Server 3 | C10: Servidor ETL - Dev | D10: LA-Mexico City2 | E10: General AZ | F10: Pay-per-use | G10: 220 | H10: hours | I10: 1 | J10: x86 | Memory-optimized | m9.large.8 | 2 vCPUs | 16GiB; Ubuntu | Ubuntu 24.04 server 64bit; General Purpose SSD | 500GB; | K10: 39.34 | L10: 39.34
B11: Elastic Volume Service 1 | C11: Elastic Volume Service | D11: LA-Mexico City2 | E11: General AZ | F11: Pay-per-use | G11: 524 | H11: hours | I11: 1 | J11: General Purpose SSD | 500GiB; | K11: 34.06 | L11: 34.06
A12: Server #2 - Gateway BI | 4vCPU 16GB RAM | Disk1: 500 GB | B12: Elastic Cloud Server 4 | C12: Gateway BI - Dev | D12: LA-Mexico City2 | E12: General AZ | F12: Pay-per-use | G12: 220 | H12: hours | I12: 1 | J12: x86 | General computing-plus | c9.large.4 | 2 vCPUs | 8GiB; Ubuntu | Ubuntu 24.04 server 64bit; General Purpose SSD | 500GB; | K12: 33.35 | L12: 33.35
B13: Elastic Volume Service 2 | C13: Elastic Volume Service | D13: LA-Mexico City2 | E13: General AZ | F13: Pay-per-use | G13: 524 | H13: hours | I13: 1 | J13: General Purpose SSD | 500GiB; | K13: 34.06 | L13: 34.06
A14: Datawarehouse Load Balancer | B14: Elastic Load Balance 2 | C14: Elastic Load Balance - Dev | D14: LA-Mexico City2 | E14: General AZ | F14: Pay-per-use | G14: 744 | H14: hours | I14: 1 | J14: General AZ | 10 LCU; | K14: 51.71 | L14: 51.71
A15: Total Price | K15: =SUM(INDIRECT(ADDRESS(1,COLUMN())&":"&ADDRESS(ROW()-1,COLUMN()))) -> 989.92 | L15: =SUM(INDIRECT(ADDRESS(1,COLUMN())&":"&ADDRESS(ROW()-1,COLUMN()))) -> 989.92
A16: The preceding price is for reference only and may vary from the final price in your bill
A19: Monthly Price | B19: =L15 -> 989.92

Sheet Storage
A5: CALCULADORA DE SERVICIOS
A7: ="Price Calculator "&TEXT(TODAY(),"mmm dd, yyyy") -> Price Calculator Aug 05, 2026
A8: Required | B8: Service | C8: Description | D8: Region | E8: AZ | F8: Billing Mode | G8: Purchase Amount | H8: Unit | I8: Quantity | J8: Specifications | K8: Unit Price (USD) | L8: Monthly Price (USD)
A9: Server Backup - PROD | B9: Cloud Backup and Recovery 1 | C9: Cloud Backup and Recovery | D9: LA-Mexico City2 | E9: General AZ | F9: Pay-per-use | G9: 744 | H9: hours | I9: 1 | J9: Server backup vault | 2000GB; | K9: 74.4 | L9: 74.4
A10: Datawarehouse Backup - PROD | B10: Object Storage Service 1 | C10: Datawarehouse Backup | D10: LA-Mexico City2 | E10: General AZ | F10: Pay-per-use | G10: 1 | I10: 1 | J10: Standard | 2TB | Single-AZ storage | Object storage | Storage Duration:1month; 0GB; 1000x 10,000 requests; 1000x 10,000 requests; 1000x 1,000 requests; 0GB; 0GB; | K10: 97.41 | L10: 97.41
A11: Server Backup - DEV | B11: Cloud Backup and Recovery 2 | C11: Cloud Backup and Recovery | D11: LA-Mexico City2 | E11: General AZ | F11: Pay-per-use | G11: 744 | H11: hours | I11: 1 | J11: Server backup vault | 2000GB; | K11: 74.4 | L11: 74.4
A12: Datawarehouse Backup - DEV | B12: Object Storage Service 2 | C12: Object Storage Service | D12: LA-Mexico City2 | E12: General AZ | F12: Pay-per-use | G12: 1 | I12: 1 | J12: Standard | 2TB | Single-AZ storage | Object storage | Storage Duration:1month; 0GB; 1000x 10,000 requests; 1000x 10,000 requests; 1000x 1,000 requests; 0GB; 0GB; | K12: 97.41 | L12: 97.41
A13: Total Price | K13: =SUM(INDIRECT(ADDRESS(1,COLUMN())&":"&ADDRESS(ROW()-1,COLUMN()))) -> 343.62 | L13: =SUM(INDIRECT(ADDRESS(1,COLUMN())&":"&ADDRESS(ROW()-1,COLUMN()))) -> 343.62
A14: The preceding price is for reference only and may vary from the final price in your bill
A17: Monthly Price | B17: =L13 -> 343.62

Sheet Connectivity
A5: CALCULADORA DE SERVICIOS
A7: ="Price Calculator "&TEXT(TODAY(),"mmm dd, yyyy") -> Price Calculator Aug 05, 2026
A8: Required | B8: Service | C8: Description | D8: Region | E8: AZ | F8: Billing Mode | G8: Purchase Amount | H8: Unit | I8: Quantity | J8: Specifications | K8: Unit Price (USD) | L8: Monthly Price (USD)
A9: Connectivity | B9: Virtual Private Network 1 | C9: Virtual Private Network | D9: LA-Mexico City2 | E9: General AZ | F9: Monthly | G9: 1 | H9: month | I9: 1 | J9: Professional 1 | 10amountsVPN Connection Groups; | K9: 209 | L9: 209
B10: NAT Gateway 1 | C10: NAT Gateway | D10: LA-Mexico City2 | E10: General AZ | F10: Pay-per-use | G10: 31 | H10: days | I10: 1 | J10: Small; | K10: 75.58 | L10: 75.58
B11: Elastic IP 1 | C11: Elastic IP | D11: LA-Mexico City2 | E11: General AZ | F11: Pay-per-use | G11: 744 | H11: hours | I11: 1 | J11: Dedicated | Dynamic BGP | Traffic | 2TB; 1 ; | K11: 169.61 | L11: 169.61
A12: Total Price | K12: =SUM(INDIRECT(ADDRESS(1,COLUMN())&":"&ADDRESS(ROW()-1,COLUMN()))) -> 454.19 | L12: =SUM(INDIRECT(ADDRESS(1,COLUMN())&":"&ADDRESS(ROW()-1,COLUMN()))) -> 454.19
A13: The preceding price is for reference only and may vary from the final price in your bill
A16: Monthly Price | B16: =L12 -> 454.19

Sheet Security
A5: CALCULADORA DE SERVICIOS
A7: ="Price Calculator "&TEXT(TODAY(),"mmm dd, yyyy") -> Price Calculator Aug 05, 2026
A8: Required | B8: Service | C8: Description | D8: Region | E8: AZ | F8: Billing Mode | G8: Purchase Amount | H8: Unit | I8: Quantity | J8: Specifications | K8: Unit Price (USD) | L8: Monthly Price (USD)
A9: Server Security | B9: Host Security Service 1 | C9: Host Security Service | D9: LA-Mexico City2 | E9: General AZ | F9: Monthly | G9: 1 | H9: month | I9: 4 | J9: Premium; | K9: 13.8 | L9: 55.2
A10: Total Price | K10: =SUM(INDIRECT(ADDRESS(1,COLUMN())&":"&ADDRESS(ROW()-1,COLUMN()))) -> 13.8 | L10: =SUM(INDIRECT(ADDRESS(1,COLUMN())&":"&ADDRESS(ROW()-1,COLUMN()))) -> 55.2
A11: The preceding price is for reference only and may vary from the final price in your bill
A14: Monthly Price | B14: =L10 -> 55.2

Sheet Support
A5: CALCULADORA DE SERVICIOS
A7: ="Price Calculator "&TEXT(TODAY(),"mmm dd, yyyy") -> Price Calculator Aug 05, 2026
A8: Required | B8: Service | C8: Description | D8: Region | E8: AZ | F8: Billing Mode | G8: Purchase Amount | H8: Unit | I8: Quantity | J8: Specifications | K8: Unit Price (USD) | L8: Monthly Price (USD)
A9: Support Plan | B9: Support Plans 1 | C9: Support Plans | D9: LA-Mexico City2 | E9: General AZ | F9: Monthly | G9: 1 | H9: month | I9: 1 | J9: Business | 3000USD/month; | K9: 300 | L9: 300
A10: Total Price | K10: =SUM(INDIRECT(ADDRESS(1,COLUMN())&":"&ADDRESS(ROW()-1,COLUMN()))) -> 300 | L10: =SUM(INDIRECT(ADDRESS(1,COLUMN())&":"&ADDRESS(ROW()-1,COLUMN()))) -> 300
A11: The preceding price is for reference only and may vary from the final price in your bill
A14: Monthly Price | B14: =L10 -> 300

Sheet tmp_v
A1: REQUIRED PART | E1: Site | H1: Site | V1: REQUIRED PART | Z1: Site | AC1: Site | AQ1: REQUIRED PART | AU1: Site | AX1: Site | BL1: REQUIRED PART | BP1: Site | BS1: Site | CG1: REQUIRED PART | CK1: Site | CN1: Site | DB1: REQUIRED PART | DF1: Site | DI1: Site | DW1: REQUIRED PART | EA1: Site | ED1: Site | ER1: REQUIRED PART | EV1: Site | EY1: Site | FM1: REQUIRED PART | FQ1: Site | FT1: Site | GH1: REQUIRED PART | GL1: Site | GO1: Site | HC1: REQUIRED PART | HG1: Site | HJ1: Site | HX1: REQUIRED PART | IB1: Site | IE1: Site
M2: REQUIRED PART | Q2: Site | T2: Site
